.gitignore
MANIFEST.in
README.txt
plonetheme.corporatevira-configure.zcml
setup.cfg
setup.py
docs/HISTORY.txt
docs/INSTALL.txt
docs/LICENSE.GPL
docs/LICENSE.txt
plonetheme/.DS_Store
plonetheme/__init__.py
plonetheme.corporatevira.egg-info/PKG-INFO
plonetheme.corporatevira.egg-info/SOURCES.txt
plonetheme.corporatevira.egg-info/dependency_links.txt
plonetheme.corporatevira.egg-info/entry_points.txt
plonetheme.corporatevira.egg-info/namespace_packages.txt
plonetheme.corporatevira.egg-info/not-zip-safe
plonetheme.corporatevira.egg-info/paster_plugins.txt
plonetheme.corporatevira.egg-info/requires.txt
plonetheme.corporatevira.egg-info/top_level.txt
plonetheme/corporatevira/.DS_Store
plonetheme/corporatevira/__init__.py
plonetheme/corporatevira/configure.zcml
plonetheme/corporatevira/profiles.zcml
plonetheme/corporatevira/setuphandlers.py
plonetheme/corporatevira/skins.zcml
plonetheme/corporatevira/tests.py
plonetheme/corporatevira/version.txt
plonetheme/corporatevira/Extensions/Install.py
plonetheme/corporatevira/browser/.DS_Store
plonetheme/corporatevira/browser/__init__.py
plonetheme/corporatevira/browser/configure.zcml
plonetheme/corporatevira/browser/interfaces.py
plonetheme/corporatevira/browser/images/README.txt
plonetheme/corporatevira/browser/stylesheets/README.txt
plonetheme/corporatevira/browser/stylesheets/main.css
plonetheme/corporatevira/profiles/.DS_Store
plonetheme/corporatevira/profiles/default/.DS_Store
plonetheme/corporatevira/profiles/default/cssregistry.xml
plonetheme/corporatevira/profiles/default/import_steps.xml
plonetheme/corporatevira/profiles/default/jsregistry.xml
plonetheme/corporatevira/profiles/default/metadata.xml
plonetheme/corporatevira/profiles/default/plonetheme.corporatevira_various.txt
plonetheme/corporatevira/profiles/default/skins.xml
plonetheme/corporatevira/profiles/uninstall/.DS_Store
plonetheme/corporatevira/profiles/uninstall/skins.xml
plonetheme/corporatevira/skins/.DS_Store
plonetheme/corporatevira/skins/plonetheme_corporatevira_custom_images/.DS_Store
plonetheme/corporatevira/skins/plonetheme_corporatevira_custom_images/CONTENT.txt
plonetheme/corporatevira/skins/plonetheme_corporatevira_custom_images/masthead.png
plonetheme/corporatevira/skins/plonetheme_corporatevira_custom_images/masthead.tif
plonetheme/corporatevira/skins/plonetheme_corporatevira_custom_templates/.DS_Store
plonetheme/corporatevira/skins/plonetheme_corporatevira_custom_templates/CONTENT.txt
