Metadata-Version: 1.0
Name: plonetheme.corporatevira
Version: 1.0
Summary: A Plone 4 theme based on plonetheme.corporatemale.
Home-page: http://github.com/espenmn/plonethmeme.corporatevira
Author: Espen Moe-Nilssen
Author-email: espen@medialog.no
License: GPL
Keywords: web zope plone theme medialog plonetheme.corporatemale
Platform: UNKNOWN
Classifier: Framework :: Plone
Classifier: Programming Language :: Python
Classifier: Topic :: Software Development :: Libraries :: Python Modules
Classifier: Framework :: Plone :: 4.0
Classifier: Framework :: Plone :: 4.1
Classifier: Framework :: Plone :: 4.2
Classifier: Framework :: Plone :: 4.3
